fastybird_devices_module/__init__.py
fastybird_devices_module/bootstrap.py
fastybird_devices_module/exceptions.py
fastybird_devices_module/logger.py
fastybird_devices_module/py.typed
fastybird_devices_module/subscriber.py
fastybird_devices_module/utils.py
fastybird_devices_module/connectors/__init__.py
fastybird_devices_module/connectors/connector.py
fastybird_devices_module/connectors/consumer.py
fastybird_devices_module/connectors/queue.py
fastybird_devices_module/entities/__init__.py
fastybird_devices_module/entities/base.py
fastybird_devices_module/entities/channel.py
fastybird_devices_module/entities/connector.py
fastybird_devices_module/entities/device.py
fastybird_devices_module/entities/property.py
fastybird_devices_module/managers/__init__.py
fastybird_devices_module/managers/base.py
fastybird_devices_module/managers/channel.py
fastybird_devices_module/managers/connector.py
fastybird_devices_module/managers/device.py
fastybird_devices_module/managers/state.py
fastybird_devices_module/repositories/__init__.py
fastybird_devices_module/repositories/channel.py
fastybird_devices_module/repositories/connector.py
fastybird_devices_module/repositories/device.py
fastybird_devices_module/repositories/state.py
fastybird_devices_module/state/__init__.py
fastybird_devices_module/state/property.py
tests/__init__.py
tests/pytests/__init__.py
tests/pytests/entities.py
tests/pytests/tests.py
tests/pytests/managers/__init__.py
tests/pytests/managers/test_connectors.py
tests/pytests/managers/test_devices.py
tests/pytests/managers/test_devices_properties.py
tests/pytests/repositories/__init__.py
tests/pytests/repositories/test_channels.py
tests/pytests/repositories/test_channels_controls.py
tests/pytests/repositories/test_channels_properties.py
tests/pytests/repositories/test_connectors.py
tests/pytests/repositories/test_connectors_controls.py
tests/pytests/repositories/test_devices.py
tests/pytests/repositories/test_devices_attributes.py
fastybird_devices_module-0.75.0.dist-info/LICENSE.md
fastybird_devices_module-0.75.0.dist-info/METADATA
fastybird_devices_module-0.75.0.dist-info/WHEEL
fastybird_devices_module-0.75.0.dist-info/top_level.txt
fastybird_devices_module-0.75.0.dist-info/RECORD
